sle_prjmgr_tools/__init__.py
sle_prjmgr_tools/cli.py
sle_prjmgr_tools/diff_modules.py
sle_prjmgr_tools/ibs_to_jira.py
sle_prjmgr_tools/incident_repos.py
sle_prjmgr_tools/jira_epics.py
sle_prjmgr_tools/list_accepted_pkgs.py
sle_prjmgr_tools/package_updates_from_xcdchk.py
sle_prjmgr_tools/packagelist_report.py
sle_prjmgr_tools/release_to.py
sle_prjmgr_tools/search_binary.py
sle_prjmgr_tools/sle_build.py
sle_prjmgr_tools/update_build_status_page.py
sle_prjmgr_tools/version.py
sle_prjmgr_tools/config/__init__.py
sle_prjmgr_tools/config/sle-prjmgr-tools.json
sle_prjmgr_tools/utils/__init__.py
sle_prjmgr_tools/utils/confluence.py
sle_prjmgr_tools/utils/jira.py
sle_prjmgr_tools/utils/osc.py
sle_prjmgr_tools-0.0.5.202303151911.dist-info/LICENSE
sle_prjmgr_tools-0.0.5.202303151911.dist-info/METADATA
sle_prjmgr_tools-0.0.5.202303151911.dist-info/WHEEL
sle_prjmgr_tools-0.0.5.202303151911.dist-info/entry_points.txt
sle_prjmgr_tools-0.0.5.202303151911.dist-info/top_level.txt
sle_prjmgr_tools-0.0.5.202303151911.dist-info/RECORD
