Metadata-Version: 2.1
Name: sle-prjmgr-tools
Version: 0.0.5.202303151911
Summary: SLE Project management tools to release SLE based products
Author: SUSE SLE Project Managers
License: EUPL-1.2
Project-URL: Source, https://github.com/openSUSE/sle-prjmgr-tools
Project-URL: Tracker, https://github.com/openSUSE/sle-prjmgr-tools/issues
Keywords: SUSE
Classifier: Programming Language :: Python :: 3
Classifier: Programming Language :: Python :: 3.6
Classifier: Programming Language :: Python :: 3.7
Classifier: Programming Language :: Python :: 3.8
Classifier: Programming Language :: Python :: 3.9
Classifier: Programming Language :: Python :: 3.10
Classifier: Programming Language :: Python :: 3.11
Requires-Python: >=3.6
License-File: LICENSE
Requires-Dist: argcomplete
Requires-Dist: requests
Requires-Dist: PyYAML
Requires-Dist: osc
Requires-Dist: jira
Requires-Dist: lxml
Requires-Dist: rpmfile
Requires-Dist: keyring
Requires-Dist: importlib-resources
Provides-Extra: docs
Requires-Dist: sphinx (>=4.3.0) ; extra == 'docs'
Requires-Dist: sphinx-rtd-theme (>=0.5.1) ; extra == 'docs'
Requires-Dist: doc8 ; extra == 'docs'
Requires-Dist: rstcheck ; extra == 'docs'
Provides-Extra: lint
Requires-Dist: black ; extra == 'lint'
Requires-Dist: pylint ; extra == 'lint'
Requires-Dist: mypy ; extra == 'lint'
Requires-Dist: types-PyYAML ; extra == 'lint'
Requires-Dist: types-requests ; extra == 'lint'
Provides-Extra: test
Requires-Dist: pytest ; extra == 'test'
